sampler/__about__.py
sampler/__init__.py
sampler/boundary_conditions/__init__.py
sampler/boundary_conditions/base.py
sampler/boundary_conditions/unit_square.py
sampler/samplers/__init__.py
sampler/samplers/base.py
sampler/samplers/gmrf.py
sampler/samplers/grf.py
sampler/samplers/unit_square.py
sampler/utils/__init__.py
sampler/utils/dtype_map.py
sampler/utils/kernels.py
sampler/utils/sparse_chol.py
sampler/utils/test.py
sampler/utils/type_aliases.py
sampler/boundary_conditions/__init__.py
sampler/boundary_conditions/base.py
sampler/boundary_conditions/unit_square.py
sampler/samplers/__init__.py
sampler/samplers/base.py
sampler/samplers/gmrf.py
sampler/samplers/grf.py
sampler/samplers/unit_square.py
sampler/utils/__init__.py
sampler/utils/dtype_map.py
sampler/utils/kernels.py
sampler/utils/sparse_chol.py
sampler/utils/test.py
sampler/utils/type_aliases.py
bspline_sampler-0.2.2.dist-info/METADATA
bspline_sampler-0.2.2.dist-info/WHEEL
bspline_sampler-0.2.2.dist-info/RECORD
